flask_banana/__init__.py
flask_banana/py.typed
Flask_Banana-0.1.2.dist-info/METADATA
Flask_Banana-0.1.2.dist-info/WHEEL
Flask_Banana-0.1.2.dist-info/top_level.txt
Flask_Banana-0.1.2.dist-info/RECORD
