Metadata-Version: 2.1
Name: Flask-Banana
Version: 0.1.2
Summary: Integrates the banana i18n library into Flask applications
Home-page: https://git.legoktm.com/legoktm/flask-banana
Author: Kunal Mehta
Author-email: legoktm@member.fsf.org
License: GPL-3.0-or-later
Platform: UNKNOWN
Requires-Python: >=3.5
Requires-Dist: Flask
Requires-Dist: banana-i18n
